{
  "_meta": {
    "description": "This file contains a serialized version of schema entities for drift.",
    "version": "1.3.0"
  },
  "options": {
    "store_date_time_values_as_text": true
  },
  "entities": [
    {
      "id": 0,
      "references": [],
      "type": "table",
      "data": {
        "name": "accounts",
        "was_declared_in_moor": false,
        "columns": [
          {
            "name": "uid",
            "getter_name": "uid",
            "moor_type": "string",
            "nullable": false,
            "customConstraints": null,
            "default_dart": null,
            "default_client_dart": null,
            "dsl_features": []
          },
          {
            "name": "email",
            "getter_name": "email",
            "moor_type": "string",
            "nullable": false,
            "customConstraints": null,
            "default_dart": null,
            "default_client_dart": null,
            "dsl_features": [
              {
                "allowed-lengths": {
                  "min": 1,
                  "max": 255
                }
              }
            ]
          },
          {
            "name": "type",
            "getter_name": "type",
            "moor_type": "string",
            "nullable": false,
            "customConstraints": null,
            "default_dart": null,
            "default_client_dart": null,
            "dsl_features": [],
            "type_converter": {
              "dart_expr": "const EnumNameConverter<AccountType>(AccountType.values)",
              "dart_type_name": "AccountType"
            }
          },
          {
            "name": "created_at",
            "getter_name": "createdAt",
            "moor_type": "dateTime",
            "nullable": false,
            "customConstraints": null,
            "default_dart": null,
            "default_client_dart": null,
            "dsl_features": []
          }
        ],
        "is_virtual": false,
        "without_rowid": false,
        "constraints": []
      }
    },
    {
      "id": 1,
      "references": [],
      "type": "table",
      "data": {
        "name": "routines",
        "was_declared_in_moor": false,
        "columns": [
          {
            "name": "id",
            "getter_name": "id",
            "moor_type": "int",
            "nullable": false,
            "customConstraints": null,
            "defaultConstraints": "PRIMARY KEY AUTOINCREMENT",
            "dialectAwareDefaultConstraints": {
              "sqlite": "PRIMARY KEY AUTOINCREMENT"
            },
            "default_dart": null,
            "default_client_dart": null,
            "dsl_features": [
              "auto-increment"
            ]
          },
          {
            "name": "api_id",
            "getter_name": "apiId",
            "moor_type": "int",
            "nullable": true,
            "customConstraints": null,
            "default_dart": null,
            "default_client_dart": null,
            "dsl_features": []
          },
          {
            "name": "version",
            "getter_name": "version",
            "moor_type": "int",
            "nullable": false,
            "customConstraints": null,
            "default_dart": null,
            "default_client_dart": "() => 0",
            "dsl_features": []
          },
          {
            "name": "name",
            "getter_name": "name",
            "moor_type": "string",
            "nullable": false,
            "customConstraints": null,
            "default_dart": null,
            "default_client_dart": null,
            "dsl_features": [
              {
                "allowed-lengths": {
                  "min": 1,
                  "max": 50
                }
              }
            ]
          },
          {
            "name": "description",
            "getter_name": "description",
            "moor_type": "string",
            "nullable": true,
            "customConstraints": null,
            "default_dart": null,
            "default_client_dart": null,
            "dsl_features": []
          },
          {
            "name": "is_current",
            "getter_name": "isCurrent",
            "moor_type": "bool",
            "nullable": false,
            "customConstraints": null,
            "defaultConstraints": "CHECK (\"is_current\" IN (0, 1))",
            "dialectAwareDefaultConstraints": {
              "sqlite": "CHECK (\"is_current\" IN (0, 1))"
            },
            "default_dart": null,
            "default_client_dart": "() => false",
            "dsl_features": []
          },
          {
            "name": "is_synced",
            "getter_name": "isSynced",
            "moor_type": "bool",
            "nullable": false,
            "customConstraints": null,
            "defaultConstraints": "CHECK (\"is_synced\" IN (0, 1))",
            "dialectAwareDefaultConstraints": {
              "sqlite": "CHECK (\"is_synced\" IN (0, 1))"
            },
            "default_dart": null,
            "default_client_dart": "() => false",
            "dsl_features": []
          },
          {
            "name": "created_at",
            "getter_name": "createdAt",
            "moor_type": "dateTime",
            "nullable": false,
            "customConstraints": null,
            "default_dart": "const CustomExpression('CURRENT_TIMESTAMP')",
            "default_client_dart": null,
            "dsl_features": []
          },
          {
            "name": "updated_at",
            "getter_name": "updatedAt",
            "moor_type": "dateTime",
            "nullable": false,
            "customConstraints": null,
            "default_dart": "const CustomExpression('CURRENT_TIMESTAMP')",
            "default_client_dart": null,
            "dsl_features": []
          }
        ],
        "is_virtual": false,
        "without_rowid": false,
        "constraints": []
      }
    },
    {
      "id": 2,
      "references": [
        1
      ],
      "type": "table",
      "data": {
        "name": "days_group",
        "was_declared_in_moor": false,
        "columns": [
          {
            "name": "id",
            "getter_name": "id",
            "moor_type": "int",
            "nullable": false,
            "customConstraints": null,
            "defaultConstraints": "PRIMARY KEY AUTOINCREMENT",
            "dialectAwareDefaultConstraints": {
              "sqlite": "PRIMARY KEY AUTOINCREMENT"
            },
            "default_dart": null,
            "default_client_dart": null,
            "dsl_features": [
              "auto-increment"
            ]
          },
          {
            "name": "api_id",
            "getter_name": "apiId",
            "moor_type": "int",
            "nullable": true,
            "customConstraints": null,
            "default_dart": null,
            "default_client_dart": null,
            "dsl_features": []
          },
          {
            "name": "index",
            "getter_name": "index",
            "moor_type": "int",
            "nullable": false,
            "customConstraints": null,
            "default_dart": null,
            "default_client_dart": null,
            "dsl_features": []
          },
          {
            "name": "version",
            "getter_name": "version",
            "moor_type": "int",
            "nullable": false,
            "customConstraints": null,
            "default_dart": null,
            "default_client_dart": "() => 0",
            "dsl_features": []
          },
          {
            "name": "day_name",
            "getter_name": "dayName",
            "moor_type": "string",
            "nullable": false,
            "customConstraints": null,
            "default_dart": null,
            "default_client_dart": null,
            "dsl_features": [
              {
                "allowed-lengths": {
                  "min": 1,
                  "max": 50
                }
              }
            ]
          },
          {
            "name": "is_synced",
            "getter_name": "isSynced",
            "moor_type": "bool",
            "nullable": false,
            "customConstraints": null,
            "defaultConstraints": "CHECK (\"is_synced\" IN (0, 1))",
            "dialectAwareDefaultConstraints": {
              "sqlite": "CHECK (\"is_synced\" IN (0, 1))"
            },
            "default_dart": null,
            "default_client_dart": "() => false",
            "dsl_features": []
          },
          {
            "name": "routine_id",
            "getter_name": "routineId",
            "moor_type": "int",
            "nullable": false,
            "customConstraints": null,
            "defaultConstraints": "REFERENCES routines (id) ON UPDATE CASCADE ON DELETE CASCADE",
            "dialectAwareDefaultConstraints": {
              "sqlite": "REFERENCES routines (id) ON UPDATE CASCADE ON DELETE CASCADE"
            },
            "default_dart": null,
            "default_client_dart": null,
            "dsl_features": [
              {
                "foreign_key": {
                  "to": {
                    "table": "routines",
                    "column": "id"
                  },
                  "initially_deferred": false,
                  "on_update": "cascade",
                  "on_delete": "cascade"
                }
              }
            ]
          }
        ],
        "is_virtual": false,
        "without_rowid": false,
        "constraints": []
      }
    },
    {
      "id": 3,
      "references": [],
      "type": "table",
      "data": {
        "name": "exercises",
        "was_declared_in_moor": false,
        "columns": [
          {
            "name": "api_id",
            "getter_name": "apiId",
            "moor_type": "string",
            "nullable": false,
            "customConstraints": null,
            "default_dart": null,
            "default_client_dart": null,
            "dsl_features": []
          },
          {
            "name": "name",
            "getter_name": "name",
            "moor_type": "string",
            "nullable": false,
            "customConstraints": null,
            "default_dart": null,
            "default_client_dart": null,
            "dsl_features": []
          },
          {
            "name": "muscle_group_code",
            "getter_name": "muscleGroupCode",
            "moor_type": "string",
            "nullable": false,
            "customConstraints": null,
            "default_dart": null,
            "default_client_dart": null,
            "dsl_features": []
          },
          {
            "name": "muscle_group_name",
            "getter_name": "muscleGroupName",
            "moor_type": "string",
            "nullable": false,
            "customConstraints": null,
            "default_dart": null,
            "default_client_dart": null,
            "dsl_features": []
          },
          {
            "name": "muscle_head_code",
            "getter_name": "muscleHeadCode",
            "moor_type": "string",
            "nullable": false,
            "customConstraints": null,
            "default_dart": null,
            "default_client_dart": null,
            "dsl_features": []
          },
          {
            "name": "muscle_head_name",
            "getter_name": "muscleHeadName",
            "moor_type": "string",
            "nullable": false,
            "customConstraints": null,
            "default_dart": null,
            "default_client_dart": null,
            "dsl_features": []
          },
          {
            "name": "aux_muscle1",
            "getter_name": "auxMuscle1",
            "moor_type": "string",
            "nullable": true,
            "customConstraints": null,
            "default_dart": null,
            "default_client_dart": null,
            "dsl_features": []
          },
          {
            "name": "aux_muscle2",
            "getter_name": "auxMuscle2",
            "moor_type": "string",
            "nullable": true,
            "customConstraints": null,
            "default_dart": null,
            "default_client_dart": null,
            "dsl_features": []
          },
          {
            "name": "aux_muscle3",
            "getter_name": "auxMuscle3",
            "moor_type": "string",
            "nullable": true,
            "customConstraints": null,
            "default_dart": null,
            "default_client_dart": null,
            "dsl_features": []
          },
          {
            "name": "laterals",
            "getter_name": "laterals",
            "moor_type": "string",
            "nullable": false,
            "customConstraints": null,
            "default_dart": null,
            "default_client_dart": null,
            "dsl_features": []
          },
          {
            "name": "description",
            "getter_name": "description",
            "moor_type": "string",
            "nullable": true,
            "customConstraints": null,
            "default_dart": null,
            "default_client_dart": null,
            "dsl_features": []
          },
          {
            "name": "tool_code",
            "getter_name": "toolCode",
            "moor_type": "string",
            "nullable": false,
            "customConstraints": null,
            "default_dart": null,
            "default_client_dart": null,
            "dsl_features": []
          },
          {
            "name": "tool_name",
            "getter_name": "toolName",
            "moor_type": "string",
            "nullable": false,
            "customConstraints": null,
            "default_dart": null,
            "default_client_dart": null,
            "dsl_features": []
          },
          {
            "name": "timestamp",
            "getter_name": "timestamp",
            "moor_type": "dateTime",
            "nullable": false,
            "customConstraints": null,
            "default_dart": null,
            "default_client_dart": "() => DateTime(2000)",
            "dsl_features": []
          }
        ],
        "is_virtual": false,
        "without_rowid": false,
        "constraints": [],
        "explicit_pk": [
          "api_id"
        ]
      }
    },
    {
      "id": 4,
      "references": [
        3,
        2
      ],
      "type": "table",
      "data": {
        "name": "routine_items",
        "was_declared_in_moor": false,
        "columns": [
          {
            "name": "id",
            "getter_name": "id",
            "moor_type": "int",
            "nullable": false,
            "customConstraints": null,
            "defaultConstraints": "PRIMARY KEY AUTOINCREMENT",
            "dialectAwareDefaultConstraints": {
              "sqlite": "PRIMARY KEY AUTOINCREMENT"
            },
            "default_dart": null,
            "default_client_dart": null,
            "dsl_features": [
              "auto-increment"
            ]
          },
          {
            "name": "api_id",
            "getter_name": "apiId",
            "moor_type": "int",
            "nullable": true,
            "customConstraints": null,
            "default_dart": null,
            "default_client_dart": null,
            "dsl_features": []
          },
          {
            "name": "index",
            "getter_name": "index",
            "moor_type": "int",
            "nullable": false,
            "customConstraints": null,
            "default_dart": null,
            "default_client_dart": null,
            "dsl_features": []
          },
          {
            "name": "notes",
            "getter_name": "notes",
            "moor_type": "string",
            "nullable": true,
            "customConstraints": null,
            "default_dart": null,
            "default_client_dart": null,
            "dsl_features": []
          },
          {
            "name": "version",
            "getter_name": "version",
            "moor_type": "int",
            "nullable": false,
            "customConstraints": null,
            "default_dart": null,
            "default_client_dart": "() => 0",
            "dsl_features": []
          },
          {
            "name": "is_synced",
            "getter_name": "isSynced",
            "moor_type": "bool",
            "nullable": false,
            "customConstraints": null,
            "defaultConstraints": "CHECK (\"is_synced\" IN (0, 1))",
            "dialectAwareDefaultConstraints": {
              "sqlite": "CHECK (\"is_synced\" IN (0, 1))"
            },
            "default_dart": null,
            "default_client_dart": "() => false",
            "dsl_features": []
          },
          {
            "name": "exercise_id",
            "getter_name": "exerciseId",
            "moor_type": "string",
            "nullable": false,
            "customConstraints": null,
            "defaultConstraints": "REFERENCES exercises (api_id) ON UPDATE CASCADE ON DELETE CASCADE",
            "dialectAwareDefaultConstraints": {
              "sqlite": "REFERENCES exercises (api_id) ON UPDATE CASCADE ON DELETE CASCADE"
            },
            "default_dart": null,
            "default_client_dart": null,
            "dsl_features": [
              {
                "foreign_key": {
                  "to": {
                    "table": "exercises",
                    "column": "api_id"
                  },
                  "initially_deferred": false,
                  "on_update": "cascade",
                  "on_delete": "cascade"
                }
              }
            ]
          },
          {
            "name": "day_id",
            "getter_name": "dayId",
            "moor_type": "int",
            "nullable": false,
            "customConstraints": null,
            "defaultConstraints": "REFERENCES days_group (id) ON UPDATE CASCADE ON DELETE CASCADE",
            "dialectAwareDefaultConstraints": {
              "sqlite": "REFERENCES days_group (id) ON UPDATE CASCADE ON DELETE CASCADE"
            },
            "default_dart": null,
            "default_client_dart": null,
            "dsl_features": [
              {
                "foreign_key": {
                  "to": {
                    "table": "days_group",
                    "column": "id"
                  },
                  "initially_deferred": false,
                  "on_update": "cascade",
                  "on_delete": "cascade"
                }
              }
            ]
          }
        ],
        "is_virtual": false,
        "without_rowid": false,
        "constraints": []
      }
    },
    {
      "id": 5,
      "references": [
        4
      ],
      "type": "table",
      "data": {
        "name": "routine_sets",
        "was_declared_in_moor": false,
        "columns": [
          {
            "name": "id",
            "getter_name": "id",
            "moor_type": "int",
            "nullable": false,
            "customConstraints": null,
            "defaultConstraints": "PRIMARY KEY AUTOINCREMENT",
            "dialectAwareDefaultConstraints": {
              "sqlite": "PRIMARY KEY AUTOINCREMENT"
            },
            "default_dart": null,
            "default_client_dart": null,
            "dsl_features": [
              "auto-increment"
            ]
          },
          {
            "name": "api_id",
            "getter_name": "apiId",
            "moor_type": "int",
            "nullable": true,
            "customConstraints": null,
            "default_dart": null,
            "default_client_dart": null,
            "dsl_features": []
          },
          {
            "name": "round_index",
            "getter_name": "roundIndex",
            "moor_type": "int",
            "nullable": false,
            "customConstraints": null,
            "default_dart": null,
            "default_client_dart": null,
            "dsl_features": []
          },
          {
            "name": "reps_count",
            "getter_name": "repsCount",
            "moor_type": "int",
            "nullable": false,
            "customConstraints": null,
            "default_dart": null,
            "default_client_dart": null,
            "dsl_features": []
          },
          {
            "name": "version",
            "getter_name": "version",
            "moor_type": "int",
            "nullable": false,
            "customConstraints": null,
            "default_dart": null,
            "default_client_dart": "() => 0",
            "dsl_features": []
          },
          {
            "name": "is_synced",
            "getter_name": "isSynced",
            "moor_type": "bool",
            "nullable": false,
            "customConstraints": null,
            "defaultConstraints": "CHECK (\"is_synced\" IN (0, 1))",
            "dialectAwareDefaultConstraints": {
              "sqlite": "CHECK (\"is_synced\" IN (0, 1))"
            },
            "default_dart": null,
            "default_client_dart": "() => false",
            "dsl_features": []
          },
          {
            "name": "routine_item_id",
            "getter_name": "routineItemId",
            "moor_type": "int",
            "nullable": false,
            "customConstraints": null,
            "defaultConstraints": "REFERENCES routine_items (id) ON UPDATE CASCADE ON DELETE CASCADE",
            "dialectAwareDefaultConstraints": {
              "sqlite": "REFERENCES routine_items (id) ON UPDATE CASCADE ON DELETE CASCADE"
            },
            "default_dart": null,
            "default_client_dart": null,
            "dsl_features": [
              {
                "foreign_key": {
                  "to": {
                    "table": "routine_items",
                    "column": "id"
                  },
                  "initially_deferred": false,
                  "on_update": "cascade",
                  "on_delete": "cascade"
                }
              }
            ]
          }
        ],
        "is_virtual": false,
        "without_rowid": false,
        "constraints": []
      }
    },
    {
      "id": 6,
      "references": [],
      "type": "table",
      "data": {
        "name": "t_sessions",
        "was_declared_in_moor": false,
        "columns": [
          {
            "name": "ts_id",
            "getter_name": "tsId",
            "moor_type": "int",
            "nullable": false,
            "customConstraints": null,
            "defaultConstraints": "PRIMARY KEY AUTOINCREMENT",
            "dialectAwareDefaultConstraints": {
              "sqlite": "PRIMARY KEY AUTOINCREMENT"
            },
            "default_dart": null,
            "default_client_dart": null,
            "dsl_features": [
              "auto-increment"
            ]
          },
          {
            "name": "day_id",
            "getter_name": "dayId",
            "moor_type": "int",
            "nullable": false,
            "customConstraints": null,
            "default_dart": null,
            "default_client_dart": null,
            "dsl_features": []
          },
          {
            "name": "day_name",
            "getter_name": "dayName",
            "moor_type": "string",
            "nullable": false,
            "customConstraints": null,
            "default_dart": null,
            "default_client_dart": null,
            "dsl_features": []
          },
          {
            "name": "started_at",
            "getter_name": "startedAt",
            "moor_type": "dateTime",
            "nullable": false,
            "customConstraints": null,
            "default_dart": null,
            "default_client_dart": null,
            "dsl_features": []
          },
          {
            "name": "finished_at",
            "getter_name": "finishedAt",
            "moor_type": "dateTime",
            "nullable": true,
            "customConstraints": null,
            "default_dart": null,
            "default_client_dart": null,
            "dsl_features": []
          },
          {
            "name": "progress",
            "getter_name": "progress",
            "moor_type": "double",
            "nullable": false,
            "customConstraints": null,
            "default_dart": "const CustomExpression('0.0')",
            "default_client_dart": null,
            "dsl_features": []
          },
          {
            "name": "api_id",
            "getter_name": "apiId",
            "moor_type": "int",
            "nullable": true,
            "customConstraints": null,
            "default_dart": null,
            "default_client_dart": null,
            "dsl_features": []
          },
          {
            "name": "version",
            "getter_name": "version",
            "moor_type": "int",
            "nullable": false,
            "customConstraints": null,
            "default_dart": "const CustomExpression('0')",
            "default_client_dart": null,
            "dsl_features": []
          },
          {
            "name": "is_synced",
            "getter_name": "isSynced",
            "moor_type": "bool",
            "nullable": false,
            "customConstraints": null,
            "defaultConstraints": "CHECK (\"is_synced\" IN (0, 1))",
            "dialectAwareDefaultConstraints": {
              "sqlite": "CHECK (\"is_synced\" IN (0, 1))"
            },
            "default_dart": "const CustomExpression('0')",
            "default_client_dart": null,
            "dsl_features": []
          }
        ],
        "is_virtual": false,
        "without_rowid": false,
        "constraints": []
      }
    },
    {
      "id": 7,
      "references": [
        6
      ],
      "type": "table",
      "data": {
        "name": "t_logs",
        "was_declared_in_moor": false,
        "columns": [
          {
            "name": "log_id",
            "getter_name": "logId",
            "moor_type": "int",
            "nullable": false,
            "customConstraints": null,
            "defaultConstraints": "PRIMARY KEY AUTOINCREMENT",
            "dialectAwareDefaultConstraints": {
              "sqlite": "PRIMARY KEY AUTOINCREMENT"
            },
            "default_dart": null,
            "default_client_dart": null,
            "dsl_features": [
              "auto-increment"
            ]
          },
          {
            "name": "exercise_id",
            "getter_name": "exerciseId",
            "moor_type": "string",
            "nullable": false,
            "customConstraints": null,
            "default_dart": null,
            "default_client_dart": null,
            "dsl_features": []
          },
          {
            "name": "exercise_index",
            "getter_name": "exerciseIndex",
            "moor_type": "int",
            "nullable": false,
            "customConstraints": null,
            "default_dart": null,
            "default_client_dart": null,
            "dsl_features": []
          },
          {
            "name": "set_index",
            "getter_name": "setIndex",
            "moor_type": "int",
            "nullable": false,
            "customConstraints": null,
            "default_dart": null,
            "default_client_dart": null,
            "dsl_features": []
          },
          {
            "name": "reps",
            "getter_name": "reps",
            "moor_type": "int",
            "nullable": false,
            "customConstraints": null,
            "default_dart": null,
            "default_client_dart": null,
            "dsl_features": []
          },
          {
            "name": "weight",
            "getter_name": "weight",
            "moor_type": "double",
            "nullable": false,
            "customConstraints": null,
            "default_dart": null,
            "default_client_dart": null,
            "dsl_features": []
          },
          {
            "name": "completed_at",
            "getter_name": "completedAt",
            "moor_type": "dateTime",
            "nullable": false,
            "customConstraints": null,
            "default_dart": null,
            "default_client_dart": null,
            "dsl_features": []
          },
          {
            "name": "api_id",
            "getter_name": "apiId",
            "moor_type": "int",
            "nullable": true,
            "customConstraints": null,
            "default_dart": null,
            "default_client_dart": null,
            "dsl_features": []
          },
          {
            "name": "version",
            "getter_name": "version",
            "moor_type": "int",
            "nullable": false,
            "customConstraints": null,
            "default_dart": "const CustomExpression('0')",
            "default_client_dart": null,
            "dsl_features": []
          },
          {
            "name": "is_synced",
            "getter_name": "isSynced",
            "moor_type": "bool",
            "nullable": false,
            "customConstraints": null,
            "defaultConstraints": "CHECK (\"is_synced\" IN (0, 1))",
            "dialectAwareDefaultConstraints": {
              "sqlite": "CHECK (\"is_synced\" IN (0, 1))"
            },
            "default_dart": "const CustomExpression('0')",
            "default_client_dart": null,
            "dsl_features": []
          },
          {
            "name": "session_id",
            "getter_name": "sessionId",
            "moor_type": "int",
            "nullable": false,
            "customConstraints": null,
            "defaultConstraints": "REFERENCES t_sessions (ts_id) ON UPDATE CASCADE ON DELETE CASCADE",
            "dialectAwareDefaultConstraints": {
              "sqlite": "REFERENCES t_sessions (ts_id) ON UPDATE CASCADE ON DELETE CASCADE"
            },
            "default_dart": null,
            "default_client_dart": null,
            "dsl_features": [
              {
                "foreign_key": {
                  "to": {
                    "table": "t_sessions",
                    "column": "ts_id"
                  },
                  "initially_deferred": false,
                  "on_update": "cascade",
                  "on_delete": "cascade"
                }
              }
            ]
          }
        ],
        "is_virtual": false,
        "without_rowid": false,
        "constraints": []
      }
    },
    {
      "id": 8,
      "references": [],
      "type": "table",
      "data": {
        "name": "measurements",
        "was_declared_in_moor": false,
        "columns": [
          {
            "name": "id",
            "getter_name": "id",
            "moor_type": "int",
            "nullable": false,
            "customConstraints": null,
            "defaultConstraints": "PRIMARY KEY AUTOINCREMENT",
            "dialectAwareDefaultConstraints": {
              "sqlite": "PRIMARY KEY AUTOINCREMENT"
            },
            "default_dart": null,
            "default_client_dart": null,
            "dsl_features": [
              "auto-increment"
            ]
          },
          {
            "name": "api_id",
            "getter_name": "apiId",
            "moor_type": "int",
            "nullable": true,
            "customConstraints": null,
            "default_dart": null,
            "default_client_dart": null,
            "dsl_features": []
          },
          {
            "name": "height",
            "getter_name": "height",
            "moor_type": "double",
            "nullable": false,
            "customConstraints": null,
            "default_dart": null,
            "default_client_dart": null,
            "dsl_features": []
          },
          {
            "name": "weight",
            "getter_name": "weight",
            "moor_type": "double",
            "nullable": false,
            "customConstraints": null,
            "default_dart": null,
            "default_client_dart": null,
            "dsl_features": []
          },
          {
            "name": "l_arm",
            "getter_name": "lArm",
            "moor_type": "double",
            "nullable": false,
            "customConstraints": null,
            "default_dart": null,
            "default_client_dart": null,
            "dsl_features": []
          },
          {
            "name": "r_arm",
            "getter_name": "rArm",
            "moor_type": "double",
            "nullable": false,
            "customConstraints": null,
            "default_dart": null,
            "default_client_dart": null,
            "dsl_features": []
          },
          {
            "name": "l_humerus",
            "getter_name": "lHumerus",
            "moor_type": "double",
            "nullable": false,
            "customConstraints": null,
            "default_dart": null,
            "default_client_dart": null,
            "dsl_features": []
          },
          {
            "name": "r_humerus",
            "getter_name": "rHumerus",
            "moor_type": "double",
            "nullable": false,
            "customConstraints": null,
            "default_dart": null,
            "default_client_dart": null,
            "dsl_features": []
          },
          {
            "name": "l_thigh",
            "getter_name": "lThigh",
            "moor_type": "double",
            "nullable": false,
            "customConstraints": null,
            "default_dart": null,
            "default_client_dart": null,
            "dsl_features": []
          },
          {
            "name": "r_thigh",
            "getter_name": "rThigh",
            "moor_type": "double",
            "nullable": false,
            "customConstraints": null,
            "default_dart": null,
            "default_client_dart": null,
            "dsl_features": []
          },
          {
            "name": "l_leg",
            "getter_name": "lLeg",
            "moor_type": "double",
            "nullable": false,
            "customConstraints": null,
            "default_dart": null,
            "default_client_dart": null,
            "dsl_features": []
          },
          {
            "name": "r_leg",
            "getter_name": "rLeg",
            "moor_type": "double",
            "nullable": false,
            "customConstraints": null,
            "default_dart": null,
            "default_client_dart": null,
            "dsl_features": []
          },
          {
            "name": "neck",
            "getter_name": "neck",
            "moor_type": "double",
            "nullable": false,
            "customConstraints": null,
            "default_dart": null,
            "default_client_dart": null,
            "dsl_features": []
          },
          {
            "name": "shoulders",
            "getter_name": "shoulders",
            "moor_type": "double",
            "nullable": false,
            "customConstraints": null,
            "default_dart": null,
            "default_client_dart": null,
            "dsl_features": []
          },
          {
            "name": "waist",
            "getter_name": "waist",
            "moor_type": "double",
            "nullable": false,
            "customConstraints": null,
            "default_dart": null,
            "default_client_dart": null,
            "dsl_features": []
          },
          {
            "name": "chest",
            "getter_name": "chest",
            "moor_type": "double",
            "nullable": false,
            "customConstraints": null,
            "default_dart": null,
            "default_client_dart": null,
            "dsl_features": []
          },
          {
            "name": "hips",
            "getter_name": "hips",
            "moor_type": "double",
            "nullable": false,
            "customConstraints": null,
            "default_dart": null,
            "default_client_dart": null,
            "dsl_features": []
          },
          {
            "name": "check_date",
            "getter_name": "checkDate",
            "moor_type": "dateTime",
            "nullable": false,
            "customConstraints": null,
            "default_dart": null,
            "default_client_dart": null,
            "dsl_features": []
          },
          {
            "name": "version",
            "getter_name": "version",
            "moor_type": "int",
            "nullable": false,
            "customConstraints": null,
            "default_dart": "const CustomExpression('0')",
            "default_client_dart": null,
            "dsl_features": []
          },
          {
            "name": "is_synced",
            "getter_name": "isSynced",
            "moor_type": "bool",
            "nullable": false,
            "customConstraints": null,
            "defaultConstraints": "CHECK (\"is_synced\" IN (0, 1))",
            "dialectAwareDefaultConstraints": {
              "sqlite": "CHECK (\"is_synced\" IN (0, 1))"
            },
            "default_dart": "const CustomExpression('0')",
            "default_client_dart": null,
            "dsl_features": []
          }
        ],
        "is_virtual": false,
        "without_rowid": false,
        "constraints": []
      }
    }
  ],
  "fixed_sql": [
    {
      "name": "accounts",
      "sql": [
        {
          "dialect": "sqlite",
          "sql": "CREATE TABLE IF NOT EXISTS \"accounts\" (\"uid\" TEXT NOT NULL, \"email\" TEXT NOT NULL, \"type\" TEXT NOT NULL, \"created_at\" TEXT NOT NULL);"
        }
      ]
    },
    {
      "name": "routines",
      "sql": [
        {
          "dialect": "sqlite",
          "sql": "CREATE TABLE IF NOT EXISTS \"routines\" (\"id\" INTEGER NOT NULL PRIMARY KEY AUTOINCREMENT, \"api_id\" INTEGER NULL, \"version\" INTEGER NOT NULL, \"name\" TEXT NOT NULL, \"description\" TEXT NULL, \"is_current\" INTEGER NOT NULL CHECK (\"is_current\" IN (0, 1)), \"is_synced\" INTEGER NOT NULL CHECK (\"is_synced\" IN (0, 1)), \"created_at\" TEXT NOT NULL DEFAULT (CURRENT_TIMESTAMP), \"updated_at\" TEXT NOT NULL DEFAULT (CURRENT_TIMESTAMP));"
        }
      ]
    },
    {
      "name": "days_group",
      "sql": [
        {
          "dialect": "sqlite",
          "sql": "CREATE TABLE IF NOT EXISTS \"days_group\" (\"id\" INTEGER NOT NULL PRIMARY KEY AUTOINCREMENT, \"api_id\" INTEGER NULL, \"index\" INTEGER NOT NULL, \"version\" INTEGER NOT NULL, \"day_name\" TEXT NOT NULL, \"is_synced\" INTEGER NOT NULL CHECK (\"is_synced\" IN (0, 1)), \"routine_id\" INTEGER NOT NULL REFERENCES routines (id) ON UPDATE CASCADE ON DELETE CASCADE);"
        }
      ]
    },
    {
      "name": "exercises",
      "sql": [
        {
          "dialect": "sqlite",
          "sql": "CREATE TABLE IF NOT EXISTS \"exercises\" (\"api_id\" TEXT NOT NULL, \"name\" TEXT NOT NULL, \"muscle_group_code\" TEXT NOT NULL, \"muscle_group_name\" TEXT NOT NULL, \"muscle_head_code\" TEXT NOT NULL, \"muscle_head_name\" TEXT NOT NULL, \"aux_muscle1\" TEXT NULL, \"aux_muscle2\" TEXT NULL, \"aux_muscle3\" TEXT NULL, \"laterals\" TEXT NOT NULL, \"description\" TEXT NULL, \"tool_code\" TEXT NOT NULL, \"tool_name\" TEXT NOT NULL, \"timestamp\" TEXT NOT NULL, PRIMARY KEY (\"api_id\"));"
        }
      ]
    },
    {
      "name": "routine_items",
      "sql": [
        {
          "dialect": "sqlite",
          "sql": "CREATE TABLE IF NOT EXISTS \"routine_items\" (\"id\" INTEGER NOT NULL PRIMARY KEY AUTOINCREMENT, \"api_id\" INTEGER NULL, \"index\" INTEGER NOT NULL, \"notes\" TEXT NULL, \"version\" INTEGER NOT NULL, \"is_synced\" INTEGER NOT NULL CHECK (\"is_synced\" IN (0, 1)), \"exercise_id\" TEXT NOT NULL REFERENCES exercises (api_id) ON UPDATE CASCADE ON DELETE CASCADE, \"day_id\" INTEGER NOT NULL REFERENCES days_group (id) ON UPDATE CASCADE ON DELETE CASCADE);"
        }
      ]
    },
    {
      "name": "routine_sets",
      "sql": [
        {
          "dialect": "sqlite",
          "sql": "CREATE TABLE IF NOT EXISTS \"routine_sets\" (\"id\" INTEGER NOT NULL PRIMARY KEY AUTOINCREMENT, \"api_id\" INTEGER NULL, \"round_index\" INTEGER NOT NULL, \"reps_count\" INTEGER NOT NULL, \"version\" INTEGER NOT NULL, \"is_synced\" INTEGER NOT NULL CHECK (\"is_synced\" IN (0, 1)), \"routine_item_id\" INTEGER NOT NULL REFERENCES routine_items (id) ON UPDATE CASCADE ON DELETE CASCADE);"
        }
      ]
    },
    {
      "name": "t_sessions",
      "sql": [
        {
          "dialect": "sqlite",
          "sql": "CREATE TABLE IF NOT EXISTS \"t_sessions\" (\"ts_id\" INTEGER NOT NULL PRIMARY KEY AUTOINCREMENT, \"day_id\" INTEGER NOT NULL, \"day_name\" TEXT NOT NULL, \"started_at\" TEXT NOT NULL, \"finished_at\" TEXT NULL, \"progress\" REAL NOT NULL DEFAULT 0.0, \"api_id\" INTEGER NULL, \"version\" INTEGER NOT NULL DEFAULT 0, \"is_synced\" INTEGER NOT NULL DEFAULT 0 CHECK (\"is_synced\" IN (0, 1)));"
        }
      ]
    },
    {
      "name": "t_logs",
      "sql": [
        {
          "dialect": "sqlite",
          "sql": "CREATE TABLE IF NOT EXISTS \"t_logs\" (\"log_id\" INTEGER NOT NULL PRIMARY KEY AUTOINCREMENT, \"exercise_id\" TEXT NOT NULL, \"exercise_index\" INTEGER NOT NULL, \"set_index\" INTEGER NOT NULL, \"reps\" INTEGER NOT NULL, \"weight\" REAL NOT NULL, \"completed_at\" TEXT NOT NULL, \"api_id\" INTEGER NULL, \"version\" INTEGER NOT NULL DEFAULT 0, \"is_synced\" INTEGER NOT NULL DEFAULT 0 CHECK (\"is_synced\" IN (0, 1)), \"session_id\" INTEGER NOT NULL REFERENCES t_sessions (ts_id) ON UPDATE CASCADE ON DELETE CASCADE);"
        }
      ]
    },
    {
      "name": "measurements",
      "sql": [
        {
          "dialect": "sqlite",
          "sql": "CREATE TABLE IF NOT EXISTS \"measurements\" (\"id\" INTEGER NOT NULL PRIMARY KEY AUTOINCREMENT, \"api_id\" INTEGER NULL, \"height\" REAL NOT NULL, \"weight\" REAL NOT NULL, \"l_arm\" REAL NOT NULL, \"r_arm\" REAL NOT NULL, \"l_humerus\" REAL NOT NULL, \"r_humerus\" REAL NOT NULL, \"l_thigh\" REAL NOT NULL, \"r_thigh\" REAL NOT NULL, \"l_leg\" REAL NOT NULL, \"r_leg\" REAL NOT NULL, \"neck\" REAL NOT NULL, \"shoulders\" REAL NOT NULL, \"waist\" REAL NOT NULL, \"chest\" REAL NOT NULL, \"hips\" REAL NOT NULL, \"check_date\" TEXT NOT NULL, \"version\" INTEGER NOT NULL DEFAULT 0, \"is_synced\" INTEGER NOT NULL DEFAULT 0 CHECK (\"is_synced\" IN (0, 1)));"
        }
      ]
    }
  ]
}